{
	"battleinthemind":{
		"imageURL":"http://sappsoftware.com/l5r/technique/kata/generalkata/battleinthemind.PNG",
		"title":"Battle in the Mind",
		"footer":"Technique, Kata, General Kata"
	},
	"breathofwindstyle":{
		"imageURL":"http://sappsoftware.com/l5r/technique/kata/generalkata/breathofwindstyle.PNG",
		"title":"Breath of Wind Style",
		"footer":"Technique, Kata, General Kata"
	},
	"crashingwavestyle":{
		"imageURL":"http://sappsoftware.com/l5r/technique/kata/generalkata/crashingwavestyle.PNG",
		"title":"Crashing Wave Style",
		"footer":"Technique, Kata, General Kata"
	},
	"crescentmoonstyle":{
		"imageURL":"http://sappsoftware.com/l5r/technique/kata/generalkata/crescentmoonstyle.PNG",
		"title":"Crescent Moon Style",
		"footer":"Technique, Kata, General Kata"
	},
	"crimsonleavesstrike":{
		"imageURL":"http://sappsoftware.com/l5r/technique/kata/generalkata/crimsonleavesstrike.PNG",
		"title":"Crimson Leaves Strike",
		"footer":"Technique, Kata, General Kata"
	},
	"disappearingworldstyle":{
		"imageURL":"http://sappsoftware.com/l5r/technique/kata/generalkata/disappearingworldstyle.PNG",
		"title":"Disappearing World Style",
		"footer":"Technique, Kata, General Kata"
	},
	"flowingwaterstrike":{
		"imageURL":"http://sappsoftware.com/l5r/technique/kata/generalkata/flowingwaterstrike.PNG",
		"title":"Flowing Water Strike",
		"footer":"Technique, Kata, General Kata"
	},
	"heartpiercingstrike":{
		"imageURL":"http://sappsoftware.com/l5r/technique/kata/generalkata/heartpiercingstrike.PNG",
		"title":"Heartpiercing Strike",
		"footer":"Technique, Kata, General Kata"
	},
	"ironinthemountainsstyle":{
		"imageURL":"http://sappsoftware.com/l5r/technique/kata/generalkata/ironinthemountainsstyle.PNG",
		"title":"Iron in the Mountains Style",
		"footer":"Technique, Kata, General Kata"
	},
	"lordhidasgrip":{
		"imageURL":"http://sappsoftware.com/l5r/technique/kata/generalkata/lordhidasgrip.PNG",
		"title":"Lord Hida’s Grip",
		"footer":"Technique, Kata, General Kata"
	},
	"lordshibasvalor":{
		"imageURL":"http://sappsoftware.com/l5r/technique/kata/generalkata/lordshibasvalor.PNG",
		"title":"Lord Shiba’s Valor",
		"footer":"Technique, Kata, General Kata"
	},
	"soaringslice":{
		"imageURL":"http://sappsoftware.com/l5r/technique/kata/generalkata/soaringslice.PNG",
		"title":"Soaring Slice",
		"footer":"Technique, Kata, General Kata"
	},
	"soulsunder":{
		"imageURL":"http://sappsoftware.com/l5r/technique/kata/generalkata/soulsunder.PNG",
		"title":"Soul Sunder",
		"footer":"Technique, Kata, General Kata"
	},
	"strikingasair":{
		"imageURL":"http://sappsoftware.com/l5r/technique/kata/generalkata/strikingasair.PNG",
		"title":"Striking as Air",
		"footer":"Technique, Kata, General Kata"
	},
	"strikingasearth":{
		"imageURL":"http://sappsoftware.com/l5r/technique/kata/generalkata/strikingasearth.PNG",
		"title":"Striking as Earth",
		"footer":"Technique, Kata, General Kata"
	},
	"strikingasfire":{
		"imageURL":"http://sappsoftware.com/l5r/technique/kata/generalkata/strikingasfire.PNG",
		"title":"Striking as Fire",
		"footer":"Technique, Kata, General Kata"
	},
	"strikingasvoid":{
		"imageURL":"http://sappsoftware.com/l5r/technique/kata/generalkata/strikingasvoid.PNG",
		"title":"Striking as Void",
		"footer":"Technique, Kata, General Kata"
	},
	"strikingaswater":{
		"imageURL":"http://sappsoftware.com/l5r/technique/kata/generalkata/strikingaswater.PNG",
		"title":"Striking as Water",
		"footer":"Technique, Kata, General Kata"
	},
	"tacticalassessment":{
		"imageURL":"http://sappsoftware.com/l5r/technique/kata/generalkata/tacticalassessment.PNG",
		"title":"Tactical Assessment",
		"footer":"Technique, Kata, General Kata"
	},
	"warriorsresolve":{
		"imageURL":"http://sappsoftware.com/l5r/technique/kata/generalkata/warriorsresolve.PNG",
		"title":"Warrior’s Resolve",
		"footer":"Technique, Kata, General Kata"
	},
	"coilingserpentstyle":{
		"imageURL":"http://sappsoftware.com/l5r/technique/kata/closecombatkata/coilingserpentstyle.PNG",
		"title":"Coiling Serpent Style",
		"footer":"Technique, Kata, Close Combat Kata,"
	},
	"iaijutsucutcrossingblade":{
		"imageURL":"http://sappsoftware.com/l5r/technique/kata/closecombatkata/iaijutsucutcrossingblade.PNG",
		"title":"Iaijutsu Cut: Crossing Blade",
		"footer":"Technique, Kata, Close Combat Kata,"
	},
	"iaijutsucutrisingblade":{
		"imageURL":"http://sappsoftware.com/l5r/technique/kata/closecombatkata/iaijutsucutrisingblade.PNG",
		"title":"Iaijutsu Cut: Rising Blade",
		"footer":"Technique, Kata, Close Combat Kata,"
	},
	"ironforeststyle":{
		"imageURL":"http://sappsoftware.com/l5r/technique/kata/closecombatkata/ironforeststyle.PNG",
		"title":"Iron Forest Style",
		"footer":"Technique, Kata, Close Combat Kata,"
	},
	"openhandstyle":{
		"imageURL":"http://sappsoftware.com/l5r/technique/kata/closecombatkata/openhandstyle.PNG",
		"title":"Open-Hand Style",
		"footer":"Technique, Kata, Close Combat Kata,"
	},
	"rushingavalanchestyle":{
		"imageURL":"http://sappsoftware.com/l5r/technique/kata/closecombatkata/rushingavalanchestyle.PNG",
		"title":"Rushing Avalanche Style",
		"footer":"Technique, Kata, Close Combat Kata,"
	},
	"spinningbladesstyle":{
		"imageURL":"http://sappsoftware.com/l5r/technique/kata/closecombatkata/spinningbladesstyle.PNG",
		"title":"Spinning Blades Style",
		"footer":"Technique, Kata, Close Combat Kata,"
	},
	"thunderclapstrike":{
		"imageURL":"http://sappsoftware.com/l5r/technique/kata/closecombatkata/thunderclapstrike.PNG",
		"title":"Thunderclap Strike",
		"footer":"Technique, Kata, Close Combat Kata,"
	},
	"veiledmenacestyle":{
		"imageURL":"http://sappsoftware.com/l5r/technique/kata/closecombatkata/veiledmenacestyle.PNG",
		"title":"Veiled Menace Style",
		"footer":"Technique, Kata, Close Combat Kata,"
	},
	"hawksprecision":{
		"imageURL":"http://sappsoftware.com/l5r/technique/kata/rangedkata/hawksprecision.PNG",
		"title":"Hawk’s Precision",
		"footer":"Technique, Kata, Ranged Kata, "
	},
	"peltinghailstyle":{
		"imageURL":"http://sappsoftware.com/l5r/technique/kata/rangedkata/peltinghailstyle.PNG",
		"title":"Pelting Hail Style",
		"footer":"Technique, Kata, Ranged Kata, "
	},
	"pinthefan":{
		"imageURL":"http://sappsoftware.com/l5r/technique/kata/rangedkata/pinthefan.PNG",
		"title":"Pin the Fan",
		"footer":"Technique, Kata, Ranged Kata, "
	}
}